consolellm/__init__.py
consolellm/app.py
consolellm/config.py
consolellm-0.1.2.dist-info/LICENSE
consolellm-0.1.2.dist-info/METADATA
consolellm-0.1.2.dist-info/WHEEL
consolellm-0.1.2.dist-info/entry_points.txt
consolellm-0.1.2.dist-info/top_level.txt
consolellm-0.1.2.dist-info/RECORD
