Metadata-Version: 2.1
Name: consolellm
Version: 0.1.2
Summary: Access Llama in your terminal.  
Home-page: https://github.com/thevoxium/consoleLLM
Author: Anshul Sharma
Author-email: thevoxium@gmail.com
Classifier: Programming Language :: Python :: 3
Classifier: License :: OSI Approved :: MIT License
Classifier: Operating System :: OS Independent
Requires-Python: >=3.6
License-File: LICENSE
Requires-Dist: markdown2 ==2.5.0
Requires-Dist: openai ==1.41.0
Requires-Dist: rich ==13.7.1
Requires-Dist: toml ==0.10.2
